sqlalchemy_mptt/__init__.py
sqlalchemy_mptt/events.py
sqlalchemy_mptt/mixins.py
sqlalchemy_mptt-0.3.0.dist-info/licenses/LICENSE.txt
sqlalchemy_mptt-0.3.0.dist-info/METADATA
sqlalchemy_mptt-0.3.0.dist-info/WHEEL
sqlalchemy_mptt-0.3.0.dist-info/top_level.txt
sqlalchemy_mptt-0.3.0.dist-info/RECORD
