Metadata-Version: 2.4
Name: sqlalchemy_mptt
Version: 0.3.0
Summary: SQLAlchemy MPTT mixins (Nested Sets)
Home-page: http://github.com/uralbash/sqlalchemy_mptt/
Author: Svintsov Dmitry
Author-email: sacrud@uralbash.ru
Maintainer: Fayaz Khan
Maintainer-email: fayaz.yusuf.khan@gmail.com
License: MIT
Classifier: Development Status :: 5 - Production/Stable
Classifier: Environment :: Console
Classifier: Environment :: Web Environment
Classifier: Intended Audience :: Developers
Classifier: Natural Language :: English
Classifier: Operating System :: OS Independent
Classifier: Programming Language :: Python
Classifier: Programming Language :: Python :: 3
Classifier: Programming Language :: Python :: 3.7
Classifier: Programming Language :: Python :: 3.8
Classifier: Programming Language :: Python :: 3.9
Classifier: Framework :: Pyramid
Classifier: Framework :: Flask
Classifier: Topic :: Internet
Classifier: Topic :: Database
Classifier: License :: OSI Approved :: MIT License
License-File: LICENSE.txt
Requires-Dist: SQLAlchemy<1.4,>=1.0.0
Dynamic: author
Dynamic: author-email
Dynamic: classifier
Dynamic: description
Dynamic: home-page
Dynamic: license
Dynamic: license-file
Dynamic: maintainer
Dynamic: maintainer-email
Dynamic: requires-dist
Dynamic: summary
